Metadata-Version: 2.1
Name: pythreadex
Version: 0.1
Summary: Utility for retrieving and plotting ThreadEx data
Home-page: https://github.com/tomerburg/pythreadex
Author: Tomer Burg
Project-URL: Source Code, https://github.com/tomerburg/pythreadex
Keywords: meteorology,weather
Platform: any
Classifier: Programming Language :: Python
Classifier: Programming Language :: Python :: 3.6
Classifier: Programming Language :: Python :: 3.7
Classifier: Intended Audience :: Science/Research
Classifier: Operating System :: OS Independent
Requires-Python: >=3.6
License-File: LICENSE
